Metadata-Version: 2.1
Name: beaglepy
Version: 0.0.2
Summary: Python binding for beagle
Home-page: https://github.com/4ment/beaglepy
Author: Mathieu Fourment
Author-email: mathieu.fourment@uts.edu.au
License: GPL3
Keywords: phylogenetics,BEAGLE,pybind11
Platform: UNKNOWN
Provides-Extra: test
